<gendarme>
	<ruleset name="default">
		<rules from="Gendarme.Rules.BadPractice.dll" exclude="DisableDebuggingCodeRule" include="*"/>
		<rules from="Gendarme.Rules.Concurrency.dll" exclude="WriteStaticFieldFromInstanceMethodRule" include="*"/>
		<rules from="Gendarme.Rules.Correctness.dll" exclude="MethodCanBeMadeStaticRule" include="*"/>
		<rules from="Gendarme.Rules.Design.dll" exclude="AvoidRefAndOutParametersRule | EnumsShouldUseInt32Rule | ConsiderConvertingMethodToPropertyRule | ConsiderAddingInterfaceRule | AvoidSmallNamespaceRule | AvoidPropertiesWithoutGetAccessorRule" include="*"/>
		<rules from="Gendarme.Rules.Design.Generic.dll" include="*"/>
		<rules from="Gendarme.Rules.Design.Linq.dll" include="*"/>
		<rules from="Gendarme.Rules.Exceptions.dll" exclude="DoNotSwallowErrorsCatchingNonSpecificExceptionsRule" include="*" />
		<rules from="Gendarme.Rules.Interoperability.dll" exclude="MarshalStringsInPInvokeDeclarationsRule" include="*"/>
		<rules from="Gendarme.Rules.Maintainability.dll" exclude="AvoidLackOfCohesionOfMethodsRule" include="*"/>
		<rules from="Gendarme.Rules.Naming.dll" exclude="UseSingularNameInEnumsUnlessAreFlagsRule | UseCorrectSuffixRule | UseCorrectCasingRule | AvoidNonAlphanumericIdentifierRule | AvoidRedundancyInTypeNameRule" include="*"/>
		<rules from="Gendarme.Rules.Performance.dll" exclude="AvoidUnusedParametersRule | AvoidUncalledPrivateCodeRule | AvoidReturningArraysOnPropertiesRule" include="*" />
		<rules from="Gendarme.Rules.Portability.dll" exclude="NewLineLiteralRule | DoNotHardcodePathsRule" include="*" />
		<rules from="Gendarme.Rules.Security.dll" include="*" />
		<rules from="Gendarme.Rules.Security.Cas.dll" include="*" />
		<rules from="Gendarme.Rules.Serialization.dll" include="*" />
		<rules from="Gendarme.Rules.Smells.dll" exclude="AvoidSwitchStatementsRule | AvoidLongParameterListsRule" include="*"/>
		<rules from="Gendarme.Rules.Ui.dll" include="*" />
	</ruleset>
</gendarme>
